hf_model_tool/__init__.py
hf_model_tool/__main__.py
hf_model_tool/api.py
hf_model_tool/asset_detector.py
hf_model_tool/cache.py
hf_model_tool/config.py
hf_model_tool/lora_manager.py
hf_model_tool/manifest.py
hf_model_tool/navigation.py
hf_model_tool/ollama.py
hf_model_tool/registry.py
hf_model_tool/ui.py
hf_model_tool/utils.py
hf_model_tool-0.2.5.dist-info/licenses/LICENSE
hf_model_tool-0.2.5.dist-info/METADATA
hf_model_tool-0.2.5.dist-info/WHEEL
hf_model_tool-0.2.5.dist-info/entry_points.txt
hf_model_tool-0.2.5.dist-info/top_level.txt
hf_model_tool-0.2.5.dist-info/RECORD
