Metadata-Version: 2.4
Name: hf-model-tool
Version: 0.2.5
Summary: A CLI tool to manage Hugging Face models.
Author-email: Zexi Chen <zzxxi.chen@gmail.com>
License: MIT
Project-URL: Homepage, https://github.com/Chen-zexi/hf-model-tool
Project-URL: Bug Tracker, https://github.com/Chen-zexi/hf-model-tool/issues
Classifier: Programming Language :: Python :: 3
Classifier: Programming Language :: Python :: 3.7
Classifier: Programming Language :: Python :: 3.8
Classifier: Programming Language :: Python :: 3.9
Classifier: Programming Language :: Python :: 3.10
Classifier: Programming Language :: Python :: 3.11
Classifier: Programming Language :: Python :: 3.12
Classifier: Operating System :: OS Independent
Classifier: Environment :: Console
Classifier: Intended Audience :: Developers
Classifier: Intended Audience :: Science/Research
Classifier: Topic :: Scientific/Engineering :: Artificial Intelligence
Classifier: Topic :: System :: Archiving
Classifier: Topic :: Utilities
Requires-Python: >=3.7
License-File: LICENSE
Requires-Dist: rich
Requires-Dist: inquirer
Requires-Dist: html2text
Requires-Dist: importlib-metadata>=1.0; python_version < "3.8"
Provides-Extra: test
Requires-Dist: pytest>=7.0.0; extra == "test"
Provides-Extra: test-cov
Requires-Dist: pytest>=7.0.0; extra == "test-cov"
Requires-Dist: pytest-cov>=4.0.0; extra == "test-cov"
Requires-Dist: pytest-mock>=3.10.0; extra == "test-cov"
Provides-Extra: dev
Requires-Dist: pytest>=7.0.0; extra == "dev"
Requires-Dist: black>=23.0.0; extra == "dev"
Requires-Dist: flake8>=6.0.0; extra == "dev"
Requires-Dist: mypy>=1.0.0; extra == "dev"
Provides-Extra: dev-full
Requires-Dist: pytest>=7.0.0; extra == "dev-full"
Requires-Dist: pytest-cov>=4.0.0; extra == "dev-full"
Requires-Dist: pytest-mock>=3.10.0; extra == "dev-full"
Requires-Dist: black>=23.0.0; extra == "dev-full"
Requires-Dist: flake8>=6.0.0; extra == "dev-full"
Requires-Dist: mypy>=1.0.0; extra == "dev-full"
Dynamic: license-file
